odoo/addons/website_local_font/README.rst
odoo/addons/website_local_font/__init__.py
odoo/addons/website_local_font/__manifest__.py
odoo/addons/website_local_font/examples/AmaticSC-Bold.woff
odoo/addons/website_local_font/examples/RacingSansOne-Regular.ttf
odoo/addons/website_local_font/examples/Trueno-wml2.otf
odoo/addons/website_local_font/i18n/it.po
odoo/addons/website_local_font/i18n/website_local_font.pot
odoo/addons/website_local_font/models/__init__.py
odoo/addons/website_local_font/models/assets.py
odoo/addons/website_local_font/models/ir_attachment.py
odoo/addons/website_local_font/readme/CONTRIBUTORS.md
odoo/addons/website_local_font/readme/DESCRIPTION.md
odoo/addons/website_local_font/readme/USAGE.md
odoo/addons/website_local_font/security/ir.model.access.csv
odoo/addons/website_local_font/static/description/AddALocalFontOption.png
odoo/addons/website_local_font/static/description/DeleteFontConfirmation.png
odoo/addons/website_local_font/static/description/FontAppliedOnWebsite.png
odoo/addons/website_local_font/static/description/FontDeleted.png
odoo/addons/website_local_font/static/description/NewlyAddedFont.png
odoo/addons/website_local_font/static/description/SaveTheFont.png
odoo/addons/website_local_font/static/description/icon.png
odoo/addons/website_local_font/static/description/index.html
odoo/addons/website_local_font/static/src/js/snippets.options.esm.js
odoo/addons/website_local_font/static/src/scss/primary_variables.scss
odoo/addons/website_local_font/static/src/scss/secondary_variables.scss
odoo/addons/website_local_font/static/src/xml/website.editor.xml
odoo/addons/website_local_font/tests/__init__.py
odoo/addons/website_local_font/tests/test_website_local_font.py
odoo_addon_website_local_font-17.0.1.0.0.4.dist-info/METADATA
odoo_addon_website_local_font-17.0.1.0.0.4.dist-info/WHEEL
odoo_addon_website_local_font-17.0.1.0.0.4.dist-info/top_level.txt
odoo_addon_website_local_font-17.0.1.0.0.4.dist-info/RECORD
